{
  "$schema": "https://mintlify.com/schema.json",
  "name": "Anam",
  "logo": {
    "dark": "/logo/anam-dark.png",
    "light": "/logo/light-3.png",
    "href": "https://anam.ai"
  },
  "favicon": "/favicon-32x32.png",
  "font": {
    "headings": {
      "family": "Roboto"
    },
    "body": {
      "family": "Roboto"
    }
  },
  "colors": {
    "primary": "#9DBBAE",
    "light": "#9DBBAE",
    "dark": "#9DBBAE",
    "background": {
      "light": "#F4F4F4",
      "dark": "#1A1D29"
    }
  },
  "background": {
    "style": "windows"
  },
  "modeToggle": {
    "default": "dark"
  },
  "rounded": "default",
  "layout": "topnav",
  "sidebar": {
    "items": "container"
  },
  "codeBlock": {
    "mode": "auto"
  },
  "navigation": [
    {
      "group": "Welcome",
      "pages": ["guides/welcome/overview"]
    },
    {
      "group": "Getting Started",
      "pages": [
        "guides/get-started/introduction",
        "guides/get-started/api-key",
        "guides/get-started/quickstart",
        "guides/get-started/production"
      ]
    },
    {
      "group": "Personas",
      "pages": [
        "guides/personas/introduction",
        "guides/personas/default-personas",
        {
          "group": "Create your own personas",
          "pages": [
            "guides/personas/create-your-own/overview",
            "guides/personas/create-your-own/create-your-own-lab",
            "guides/personas/create-your-own/create-your-own-api"
          ]
        },
        "guides/personas/custom-brains"
      ]
    },
    {
      "group": "Build with Anam",
      "pages": [
        "guides/build-with-anam/creating-smarter-personas",
        "guides/build-with-anam/examples"
      ]
    },
    {
      "group": "Knowledge Base",
      "pages": ["guides/faq/faq"]
    },
    {
      "group": "SDK Reference",
      "pages": [
        "sdk-reference/introduction",
        "sdk-reference/basic-usage",
        "sdk-reference/production",
        "sdk-reference/talk-commands",
        "sdk-reference/audio-control",
        "sdk-reference/configuration",
        "sdk-reference/events"
      ]
    },
    {
      "group": "API Reference",
      "pages": [
        "api-reference/introduction",
        {
          "group": "Endpoints",
          "pages": [
            {
              "group": "Auth",
              "pages": ["api-reference/auth/get-v1authsession-token"]
            },
            {
              "group": "Personas",
              "pages": [
                "api-reference/persona/get-v1personaspresets",
                "api-reference/persona/get-v1personaspresets-1",
                "api-reference/persona/get-v1personas",
                "api-reference/persona/get-v1personas-1",
                "api-reference/persona/post-v1personas",
                "api-reference/persona/put-v1personas",
                "api-reference/persona/delete-v1personas"
              ]
            }
          ]
        }
      ]
    }
  ],
  "topbarLinks": [
    {
      "name": "Support",
      "url": "mailto:support@anam.ai"
    }
  ],
  "topbarCtaButton": {
    "name": "Anam Lab",
    "url": "https://lab.anam.ai"
  },
  "tabs": [
    {
      "name": "User Guides",
      "url": "guides"
    },
    {
      "name": "SDK Reference",
      "url": "sdk-reference"
    },
    {
      "name": "API Reference",
      "url": "api-reference"
    }
  ],
  "openapi": "https://api.anam.ai/api-json",
  "api": {
    "baseUrl": "https://api.anam.ai",
    "playground": {
      "mode": "show"
    }
  }
}
